README.md
setup.py
goprocam/GoProCamera.py
goprocam/__init__.py
goprocam/constants.py
goprocam/exceptions.py
goprocam.egg-info/PKG-INFO
goprocam.egg-info/SOURCES.txt
goprocam.egg-info/dependency_links.txt
goprocam.egg-info/not-zip-safe
goprocam.egg-info/top_level.txt