Metadata-Version: 2.1
Name: goprocam
Version: 3.0.8
Summary: GoPro WiFi API Wrapper for Python - Compatible with HERO3, HERO3+, HERO4, HERO5, HERO+, HERO6
Home-page: http://github.com/konradit/gopro-py-api
Author: Konrad Iturbe
Author-email: mail@chernowii.com
License: MIT
Platform: UNKNOWN
